aliyun_sdk_secretsmanager_common_plugin/__init__.py
aliyun_sdk_secretsmanager_common_plugin/ak_expire_handler.py
aliyun_sdk_secretsmanager_common_plugin/aliyun_sdk_secretsmanager_plugins_manager.py
aliyun_sdk_secretsmanager_common_plugin/default_ak_expire_handler.py
aliyun_sdk_secretsmanager_common_plugin/secretsmanager_plugin_builder.py
aliyun_sdk_secretsmanager_common_plugin/secretsmanager_plugin_credential_updater.py
aliyun_sdk_secretsmanager_common_plugin/auth/__init__.py
aliyun_sdk_secretsmanager_common_plugin/auth/secretsmanager_plugin_credentials.py
aliyun_sdk_secretsmanager_common_plugin/model/__init__.py
aliyun_sdk_secretsmanager_common_plugin/model/monitor_message_info.py
aliyun_sdk_secretsmanager_common_plugin/model/secretsmanager_plugin_credentials_provider.py
aliyun_sdk_secretsmanager_common_plugin/service/__init__.py
aliyun_sdk_secretsmanager_common_plugin/service/default_plugins_credentials_loader.py
aliyun_sdk_secretsmanager_common_plugin/service/default_secretsmanager_plugin_cache_hook.py
aliyun_sdk_secretsmanager_common_plugin/service/monitor_cache_secret_store_strategy.py
aliyun_sdk_secretsmanager_common_plugin/service/monitor_memory_cache_secret_store_strategy.py
aliyun_sdk_secretsmanager_common_plugin/service/rotate_ak_secret_refresh_secret_strategy.py
aliyun_sdk_secretsmanager_common_plugin/service/secret_exchange.py
aliyun_sdk_secretsmanager_common_plugin/service/secret_recovery_strategy.py
aliyun_sdk_secretsmanager_common_plugin/service/secretsmanager_plugin_cache_hook.py
aliyun_sdk_secretsmanager_common_plugin/service/secretsmanager_plugin_credentials_loader.py
aliyun_sdk_secretsmanager_common_plugin/utils/__init__.py
aliyun_sdk_secretsmanager_common_plugin/utils/config_loader.py
aliyun_sdk_secretsmanager_common_plugin/utils/consts.py
aliyun_sdk_secretsmanager_common_plugin/utils/credentials_utils.py
aliyun_sdk_secretsmanager_common_plugin/utils/date_utils.py
aliyun_sdk_secretsmanager_common_plugin/utils/monitor_message_utils.py
jepson_aliyun_sdk_common_managed_credentials_provider-0.1.5.dist-info/METADATA
jepson_aliyun_sdk_common_managed_credentials_provider-0.1.5.dist-info/WHEEL
jepson_aliyun_sdk_common_managed_credentials_provider-0.1.5.dist-info/top_level.txt
jepson_aliyun_sdk_common_managed_credentials_provider-0.1.5.dist-info/RECORD
