Metadata-Version: 2.1
Name: jepson-aliyun-sdk-common-managed-credentials-provider
Version: 0.1.5
Summary: Aliyun SDK Common Managed Credentials Provider
Author: Aliyun
Maintainer: Aliyun
License: Apache License 2.0
Keywords: aliyun,kms,common
Classifier: Development Status :: 5 - Production/Stable
Classifier: Programming Language :: Python
Classifier: Programming Language :: Python :: 2
Classifier: Programming Language :: Python :: 2.7
Classifier: Programming Language :: Python :: 3
Classifier: Programming Language :: Python :: 3.6
Classifier: Programming Language :: Python :: 3.7
Classifier: Programming Language :: Python :: 3.8
Classifier: Programming Language :: Python :: 3.9
Classifier: Programming Language :: Python :: Implementation :: CPython
Classifier: Topic :: Security
Requires-Dist: jepson-aliyun-secret-manager-client ==0.1.5
Requires-Dist: requests <=2.0.0 ; python_version == "2.7"
Requires-Dist: requests >=0.10.1 ; python_version >= "3"
